rosetta/ANN_Module.py
rosetta/DB_Module.py
rosetta/__init__.py
rosetta/__version__.py
rosetta/rosetta.py
rosetta/sqlite/Rosetta.sqlite
rosetta_soil-0.1.2.dist-info/LICENSE
rosetta_soil-0.1.2.dist-info/LICENSE.notes
rosetta_soil-0.1.2.dist-info/METADATA
rosetta_soil-0.1.2.dist-info/WHEEL
rosetta_soil-0.1.2.dist-info/top_level.txt
rosetta_soil-0.1.2.dist-info/RECORD
